{
  "updated_at": "2025-01-08T09:02:20.459Z",
  "date_range_all_from": "2024-01-09T07:53:38.000Z",
  "date_range_all_to": "2025-01-05T12:44:02.000Z",
  "date_range_from": "2024-12-07T00:00:00.000Z",
  "date_range_to": "2025-01-05T23:59:59.999Z",
  "parseWarnings": 4,
  "_comment": "auto generated; do not manually modify",
  "_time_dsc": "all times are in seconds",
  "unit_time_stats": {
    "first_unit_reaction": {
      "sum": 3555,
      "mean": 123,
      "q1": 82,
      "median": 118,
      "q3": 149,
      "min": 7,
      "max": 336
    },
    "travel": {
      "sum": 22951,
      "mean": 574,
      "q1": 300,
      "median": 599,
      "q3": 806,
      "min": 60,
      "max": 1478
    },
    "to_scene": {
      "sum": 33606,
      "mean": 840,
      "q1": 438,
      "median": 753,
      "q3": 1133,
      "min": 102,
      "max": 2079
    },
    "on_scene": {
      "sum": 73428,
      "mean": 1791,
      "q1": 704,
      "median": 1132,
      "q3": 2544,
      "min": 93,
      "max": 5641
    }
  },
  "personnel_stats": {
    "time_on_incidents": {
      "sum": 143940,
      "mean": 4798,
      "q1": 1880,
      "median": 2818,
      "q3": 4640,
      "min": 825,
      "max": 46158
    },
    "num_per_incidents": {
      "mean": 2.6,
      "q1": 1,
      "median": 2,
      "q3": 3,
      "min": 0,
      "max": 14
    },
    "num_unique_responders": 21
  },
  "region_stats": {
    "central": {
      "incident_types": {
        "medical_rescue": 7,
        "fire": 5,
        "downgraded": 10,
        "cancelled": 2,
        "other": 0
      },
      "num_incidents": 24,
      "unit_travel_time": {
        "sum": 14565,
        "mean": 470,
        "q1": 274,
        "median": 399,
        "q3": 621,
        "min": 60,
        "max": 972
      }
    },
    "north": {
      "incident_types": {
        "medical_rescue": 1,
        "fire": 1,
        "downgraded": 0,
        "cancelled": 0,
        "other": 0
      },
      "num_incidents": 2,
      "unit_travel_time": {
        "sum": 5365,
        "mean": 1073,
        "q1": 828,
        "median": 1046,
        "q3": 1370,
        "min": 643,
        "max": 1478
      }
    },
    "south": {
      "incident_types": {
        "medical_rescue": 3,
        "fire": 1,
        "downgraded": 0,
        "cancelled": 0,
        "other": 0
      },
      "num_incidents": 4,
      "unit_travel_time": {
        "sum": 3021,
        "mean": 755,
        "q1": 696,
        "median": 750,
        "q3": 809,
        "min": 682,
        "max": 840
      }
    }
  },
  "incident_stats": {
    "types": {
      "medical_rescue": 11,
      "fire": 7,
      "downgraded": 10,
      "cancelled": 2,
      "other": 0
    },
    "num_incidents_last_365_days": 465,
    "num_incidents": 30,
    "num_daytime_incidents": 17,
    "num_nighttime_incidents": 13,
    "incident_times": {
      "sum": 65495,
      "mean": 2183,
      "q1": 1120,
      "median": 1593,
      "q3": 2581,
      "min": 275,
      "max": 6341
    },
    "num_overlapping_incidents": 4,
    "num_per_day": {
      "sum": 30,
      "mean": 1,
      "q1": 0,
      "median": 1,
      "q3": 2,
      "min": 0,
      "max": 3
    }
  },
  "apparatus_stats": {
    "num_per_incident": {
      "mean": 2.3,
      "q1": 1,
      "median": 1.5,
      "q3": 2.8,
      "min": 1,
      "max": 11
    },
    "num_unique_used": 14
  }
}